{
"companyName": "DefaultCompany",
"productName": "NightLightz",
"productVersion": "0.1",
"dataUrl": "NightLight.data.unityweb",
"wasmCodeUrl": "NightLight.wasm.code.unityweb",
"wasmFrameworkUrl": "NightLight.wasm.framework.unityweb",
"graphicsAPI": ["WebGL 2.0","WebGL 1.0"],
"webglContextAttributes": {"preserveDrawingBuffer": false},
"splashScreenStyle": "Dark",
"backgroundColor": "#231F20",
"cacheControl": {"default": "must-revalidate"},
"developmentBuild": true,
"multithreading": false,
"unityVersion": "2019.3.0a5"
}